sembicho/__init__.py
sembicho/__main__.py
sembicho/__version__.py
sembicho/auth_module.py
sembicho/cli.py
sembicho/complexity_engine.py
sembicho/javascript_linting.py
sembicho/linting_engine.py
sembicho/python_linting.py
sembicho/quality_integrator.py
sembicho/sbom_scanner.py
sembicho/scanner.py
sembicho_cli-2.6.5.dist-info/licenses/LICENSE
sembicho_cli-2.6.5.dist-info/METADATA
sembicho_cli-2.6.5.dist-info/WHEEL
sembicho_cli-2.6.5.dist-info/entry_points.txt
sembicho_cli-2.6.5.dist-info/top_level.txt
sembicho_cli-2.6.5.dist-info/RECORD
