Metadata-Version: 2.4
Name: sembicho-cli
Version: 2.6.5
Summary: SAST + SBOM (CycloneDX/SPDX) + CVE Scanning (OSV/Safety/NVD) - Análisis de seguridad empresarial completo
Home-page: https://github.com/Claudio-Barrios-83/sembicho-cli
Author: SemBicho Team
Author-email: info@sembicho.com
Project-URL: Bug Tracker, https://github.com/Claudio-Barrios-83/sembicho-cli/issues
Project-URL: Documentation, https://github.com/Claudio-Barrios-83/sembicho-cli
Project-URL: Source Code, https://github.com/Claudio-Barrios-83/sembicho-cli
Keywords: security,static-analysis,vulnerability-scanner,code-analysis,security-testing,devops,ci-cd,python,javascript,java,php,go,csharp,sast,security-scanner,vulnerability-detection
Classifier: Development Status :: 5 - Production/Stable
Classifier: Intended Audience :: Developers
Classifier: Intended Audience :: Information Technology
Classifier: Topic :: Security
Classifier: Topic :: Software Development :: Quality Assurance
Classifier: Topic :: Software Development :: Testing
Classifier: License :: OSI Approved :: MIT License
Classifier: Programming Language :: Python :: 3
Classifier: Programming Language :: Python :: 3.7
Classifier: Programming Language :: Python :: 3.8
Classifier: Programming Language :: Python :: 3.9
Classifier: Programming Language :: Python :: 3.10
Classifier: Programming Language :: Python :: 3.11
Classifier: Programming Language :: Python :: 3.12
Classifier: Operating System :: OS Independent
Classifier: Environment :: Console
Requires-Python: >=3.7
License-File: LICENSE
Requires-Dist: requests>=2.31.0
Requires-Dist: urllib3>=2.0.7
Requires-Dist: python-dateutil>=2.8.2
Requires-Dist: chardet>=5.2.0
Requires-Dist: jinja2>=3.1.2
Requires-Dist: markupsafe>=2.1.3
Requires-Dist: pyyaml>=6.0.1
Requires-Dist: toml>=0.10.2
Requires-Dist: regex>=2023.8.8
Requires-Dist: keyring>=24.3.0
Requires-Dist: colorama>=0.4.6
Requires-Dist: radon>=6.0.1
Provides-Extra: cve
Requires-Dist: safety>=2.3.0; extra == "cve"
Provides-Extra: quality
Requires-Dist: radon>=6.0.1; extra == "quality"
Requires-Dist: flake8>=6.0.0; extra == "quality"
Requires-Dist: black>=23.0.0; extra == "quality"
Requires-Dist: pylint>=3.0.0; extra == "quality"
Provides-Extra: all
Requires-Dist: radon>=6.0.1; extra == "all"
Requires-Dist: flake8>=6.0.0; extra == "all"
Requires-Dist: black>=23.0.0; extra == "all"
Requires-Dist: pylint>=3.0.0; extra == "all"
Dynamic: author
Dynamic: author-email
Dynamic: classifier
Dynamic: description
Dynamic: description-content-type
Dynamic: home-page
Dynamic: keywords
Dynamic: license-file
Dynamic: project-url
Dynamic: provides-extra
Dynamic: requires-dist
Dynamic: requires-python
Dynamic: summary
